dataqa/__init__.py
dataqa/column_mapping.py
dataqa/infer_schema.py
dataqa/publish.py
dataqa/tests/__init__.py
dataqa/tests/conftest.py
dataqa/tests/test_infer_schema.py
dataqa/tests/test_validate_schema.py
dataqa-2.0.3.dist-info/LICENSE
dataqa-2.0.3.dist-info/WHEEL
dataqa-2.0.3.dist-info/METADATA
dataqa-2.0.3.dist-info/RECORD
