Metadata-Version: 2.1
Name: dataqa
Version: 2.0.3
Summary: Python Client library for DataQA
Home-page: https://dataqa.ai
Author: Maria Mestre
Author-email: maria@dataqa.ai
Requires-Python: >=3.8,<4.0
Classifier: Programming Language :: Python :: 3
Classifier: Programming Language :: Python :: 3.8
Classifier: Programming Language :: Python :: 3.9
Classifier: Programming Language :: Python :: 3.10
Requires-Dist: pandas (>=1.4.4,<2.0.0)
Requires-Dist: pytest (>=7.1.3,<8.0.0)
Requires-Dist: requests (>=2.28.1,<3.0.0)
Project-URL: Documentation, https://docs.dataqa.ai
Project-URL: Repository, https://github.com/dataqa/dataqa-python
